gitsrc.py
gitupload-1.0.2.dist-info/LICENSE
gitupload-1.0.2.dist-info/METADATA
gitupload-1.0.2.dist-info/WHEEL
gitupload-1.0.2.dist-info/top_level.txt
gitupload-1.0.2.dist-info/RECORD
