Metadata-Version: 2.1
Name: gitupload
Version: 1.0.2
Summary: A Python package to upload a local repository to Github from your Local Machine without git commands
Home-page: https://github.com/phlakhani/GitUploader
Author: Piyush Lakhani
Author-email: piyushlakhani.net@gmail.com
License: UNKNOWN
Platform: UNKNOWN
Classifier: Programming Language :: Python :: 3
Classifier: License :: OSI Approved :: MIT License
Classifier: Operating System :: Microsoft :: Windows :: Windows 10
Classifier: Operating System :: Microsoft :: Windows :: Windows 8.1
